LICENSE
MANIFEST.in
README.txt
setup.py
bin/nagiosharder
nagiosharder/__init__.py
nagiosharder/html.py
nagiosharder/parse.py
nagiosharder.egg-info/PKG-INFO
nagiosharder.egg-info/SOURCES.txt
nagiosharder.egg-info/dependency_links.txt
nagiosharder.egg-info/requires.txt
nagiosharder.egg-info/top_level.txt