Metadata-Version: 1.0
Name: nagiosharder
Version: 0.2.5
Summary: lib and cli interface to nagios status.cgi
Home-page: git://skurih.in/nagios-harder.git
Author: Alexandr Skurikhin
Author-email: a@skurih.in
License: Copyright (c) 2012 Alexandr Skurikhin
